pdhelper/__init__.py
pdhelper/left_merge.py
pdhelper/parallel_dataframe.py
pdhelper/parallel_read.py
pandashelper-2.1.1.dist-info/LICENSE
pandashelper-2.1.1.dist-info/METADATA
pandashelper-2.1.1.dist-info/WHEEL
pandashelper-2.1.1.dist-info/top_level.txt
pandashelper-2.1.1.dist-info/RECORD
